musamusa_atext/aboutproject.py
musamusa_atext/annotatedstring.py
musamusa_atext/annotatedtext.py
musamusa_atext-0.1.6.dist-info/LICENSE
musamusa_atext-0.1.6.dist-info/WHEEL
musamusa_atext-0.1.6.dist-info/METADATA
musamusa_atext-0.1.6.dist-info/RECORD
