Metadata-Version: 2.1
Name: musamusa-atext
Version: 0.1.6
Summary: MusaMusa::AnnotatedText
License: GPLv3
Author: suizokukan
Author-email: suizokukan@orange.fr
Requires-Python: >=3.9,<4.0
Classifier: License :: Other/Proprietary License
Classifier: Programming Language :: Python :: 3
Classifier: Programming Language :: Python :: 3.9
Requires-Dist: musamusa-textref (>=0.2.2,<0.3.0)
